README.rst
setup.cfg
setup.py
SmokeAPI.egg-info/PKG-INFO
SmokeAPI.egg-info/SOURCES.txt
SmokeAPI.egg-info/dependency_links.txt
SmokeAPI.egg-info/requires.txt
SmokeAPI.egg-info/top_level.txt
smokeapi/__init__.py
smokeapi/findspam.py
smokeapi/smoke_test.py
smokeapi/smokeapi.py