Metadata-Version: 1.1
Name: SmokeAPI
Version: 0.2.0
Summary: Library for interacting with the MetaSmoke API
Home-page: https://github.com/AWegnerGitHub/SmokeAPI
Author: Andrew Wegner
Author-email: pypi@andrewwegner.com
License: MIT
Keywords: stackexchange
Platform: UNKNOWN
Classifier: Development Status :: 4 - Beta
Classifier: Intended Audience :: Developers
Classifier: License :: OSI Approved :: MIT License
Classifier: Programming Language :: Python :: 2.7
Classifier: Programming Language :: Python :: 3.3
Classifier: Programming Language :: Python :: 3.4
Classifier: Programming Language :: Python :: 3.5
Classifier: Natural Language :: English
Classifier: Operating System :: OS Independent
Classifier: Topic :: Software Development :: Libraries :: Python Modules
